{"trial_id": "0036", "hyperparameters": {"space": [{"class_name": "Int", "config": {"name": "units", "default": null, "conditions": [], "min_value": 32, "max_value": 256, "step": 16, "sampling": "linear"}}, {"class_name": "Float", "config": {"name": "dropout_1", "default": 0.25, "conditions": [], "min_value": 0.1, "max_value": 0.5, "step": null, "sampling": "linear"}}, {"class_name": "Float", "config": {"name": "dropout_2", "default": 0.25, "conditions": [], "min_value": 0.1, "max_value": 0.5, "step": null, "sampling": "linear"}}, {"class_name": "Choice", "config": {"name": "learning_rate", "default": 0.0001, "conditions": [], "values": [0.0001, 0.001, 0.01, 0.1], "ordered": true}}], "values": {"units": 208, "dropout_1": 0.36219155537252024, "dropout_2": 0.4609108997819402, "learning_rate": 0.1, "tuner/epochs": 6, "tuner/initial_epoch": 2, "tuner/bracket": 3, "tuner/round": 1, "tuner/trial_id": "0006"}}, "metrics": {"metrics": {"AUC": {"direction": "max", "observations": [{"value": [0.8399527072906494], "step": 2}]}, "accuracy": {"direction": "max", "observations": [{"value": [0.760869562625885], "step": 2}]}, "loss": {"direction": "min", "observations": [{"value": [2.2547414302825928], "step": 2}]}, "val_AUC": {"direction": "max", "observations": [{"value": [0.8907563090324402], "step": 2}]}, "val_accuracy": {"direction": "max", "observations": [{"value": [0.9032257795333862], "step": 2}]}, "val_loss": {"direction": "min", "observations": [{"value": [3.0955684185028076], "step": 2}]}}}, "score": 0.9032257795333862, "best_step": 2, "status": "COMPLETED", "message": null}