{"trial_id": "0020", "hyperparameters": {"space": [{"class_name": "Int", "config": {"name": "units", "default": null, "conditions": [], "min_value": 32, "max_value": 256, "step": 16, "sampling": "linear"}}, {"class_name": "Float", "config": {"name": "dropout_1", "default": 0.25, "conditions": [], "min_value": 0.1, "max_value": 0.5, "step": null, "sampling": "linear"}}, {"class_name": "Float", "config": {"name": "dropout_2", "default": 0.25, "conditions": [], "min_value": 0.1, "max_value": 0.5, "step": null, "sampling": "linear"}}, {"class_name": "Choice", "config": {"name": "learning_rate", "default": 0.0001, "conditions": [], "values": [0.0001, 0.001, 0.01, 0.1], "ordered": true}}], "values": {"units": 80, "dropout_1": 0.25602969584127255, "dropout_2": 0.24320913470112676, "learning_rate": 0.001, "tuner/epochs": 2, "tuner/initial_epoch": 0, "tuner/bracket": 3, "tuner/round": 0}}, "metrics": {"metrics": {"AUC": {"direction": "max", "observations": [{"value": [0.7784870266914368], "step": 1}]}, "accuracy": {"direction": "max", "observations": [{"value": [0.760869562625885], "step": 1}]}, "loss": {"direction": "min", "observations": [{"value": [0.624015212059021], "step": 1}]}, "val_AUC": {"direction": "max", "observations": [{"value": [0.9201680421829224], "step": 1}]}, "val_accuracy": {"direction": "max", "observations": [{"value": [0.8387096524238586], "step": 1}]}, "val_loss": {"direction": "min", "observations": [{"value": [0.5305309295654297], "step": 1}]}}}, "score": 0.8387096524238586, "best_step": 1, "status": "COMPLETED", "message": null}